{
    "head": {
        "status": "200",
        "message": "susccess",
        "module": "Activity"
    },
    "body": {
        "screeninfo": {
            "titlestatusApproved": "Approved!",
            "titlestatusUnapproved": "Unapproved!",
            "titlestatusRejected": "Rejected!",
            "textactivity": "Activity name",
            "textyear": "Year",
            "textterm": "Term",
            "textstartdate": "Start date",
            "textfinishdate": "Finish date",
            "texttime": "Total time",
            "texttimestatus": "( hr : min)",
            "textvenue": "Venue",
            "edtapprover": "Approver",
            "textdetail": "Detail",
            "buttonleft": "Edit",
            "buttonright": "Delete"
        },
        "activity": [
            {
                "id": "1",
                "name": "5555โครงการส่งเสริมสุขภาวะที่ดีและมีสุนทรียภาพของผู้เรียน",
                "year": "2017",
                "term": "1",
                "startdate": "2017-01-01",
                "finishdate": "2017-12-31",
                "time": " 05:30 ",
                "venue": "Room ITC513",
                "approver": "3. จิรทีปต์ - รุ่งเรืองตลอดกาลนาน",
                "detail": "Detail 1กิจกรรม ",
                "status": "Approved!",
                "color": "#B6FFCE"
            },
            {
                "id": "2",
                "name": "โครงการส่งเสริม คุณธรรม จริยธรรม และค่านิยมที่พึงประสงค์ ของผู้เรียน",
                "year": "2017",
                "term": "1",
                "startdate": "2017-01-01",
                "finishdate": "2017-12-31",
                "time": " 05:30 ",
                "venue": "RoomSD9546",
                "approver": "4. ณัฐปคัลภ์ - ปราชญ์ผู้องอาจ",
                "detail": "Detail 1กิจกรรมโครงการส่งเสริม คุณธรรม จริยธรรม และค่านิยมที่พึงประสงค์ ของผู้เรียน ",
                "status": "Rejected!",
                "color": "#FFCECE"
            },
            {
                "id": "3",
                "name": "โครงการพัฒนาผู้เรียนให้มีทักษะในการแสวงหาความรู้ด้วยตนเอง รักเรียนรู้ และพัฒนาตนเองอย่างต่อเนื่อง",
                "year": "2017",
                "term": "1",
                "startdate": "2017-01-01",
                "finishdate": "2017-12-31",
                "time": " 05:30 ",
                "venue": "Room CL101",
                "approver": "11. อิงครัต - ผู้ยินดีในความรู้",
                "detail": "Detail 1กิจกรรมโครงการพัฒนาผู้เรียนให้มีทักษะในการแสวงหาความรู้ด้วยตนเอง รักเรียนรู้ และพัฒนาตนเองอย่างต่อเนื่อง ",
                "status": "Unapproved!",
                "color": "#FAFFBE"
            },
            {
                "id": "4",
                "name": "โครงการพัฒนาผู้เรียนให้มีความสามารถในการคิดอย่างเป็นระบบ คิดสร้างสรรค์ ตัดสินใจแก้ปัญหาได้อย่างมีสติสมเหตุผล",
                "year": "2017",
                "term": "1",
                "startdate": "2017-01-01",
                "finishdate": "2017-12-31",
                "time": " 05:30 ",
                "venue": "Room SVT546",
                "approver": "23. จิรัฎฐ์ - ดำรงมั่น อยู่นาน",
                "detail": "Detail 1กิจกรรมโครงการพัฒนาผู้เรียนให้มีความสามารถในการคิดอย่างเป็นระบบ คิดสร้างสรรค์ ตัดสินใจแก้ปัญหาได้อย่างมีสติสมเหตุผล ",
                "status": "Approved!",
                "color": "#C7FFAD"
            },
            {
                "id": "5",
                "name": "โครงการพัฒนาระบบบริหารสถานศึกษา",
                "year": "2017",
                "term": "1",
                "startdate": "2017-01-01",
                "finishdate": "2017-12-31",
                "time": " 05:30 ",
                "venue": "Room SC652",
                "approver": "39. ฐิตธีร์ - ปราชญ์ผุ้มั่นคง",
                "detail": "Detail กิจกรรม ",
                "status": "Unapproved!",
                "color": "#FAFFBE"
            },
            {
                "id": "6",
                "name": "โครงการพัฒนาครูให้ปฏิบัติงานตามบทบาทหน้าที่อย่างมีประสิทธิภาพและเกิดประสิทธิผล",
                "year": "2017",
                "term": "1",
                "startdate": "2017-01-01",
                "finishdate": "2017-12-31",
                "time": " 05:30 ",
                "venue": "Room SC302",
                "approver": "49. อุกฤษฎ์ - ประเสริฐสุด",
                "detail": "Detail 2 กิจกรรมโครงการพัฒนาครูให้ปฏิบัติงานตามบทบาทหน้าที่อย่างมีประสิทธิภาพและเกิดประสิทธิผล ",
                "status": "Rejected!",
                "color": "#FFCECE"
            }
        ]
    }
}